thepay/__init__.py
thepay/config.py
thepay/dataApi.py
thepay/gateApi.py
thepay/payment.py
thepay/test_dataApi.py
thepay/test_gateApi.py
thepay/test_payment.py
thepay/utils.py
nijel_thepay-0.5.dist-info/METADATA
nijel_thepay-0.5.dist-info/WHEEL
nijel_thepay-0.5.dist-info/top_level.txt
nijel_thepay-0.5.dist-info/RECORD
