Metadata-Version: 2.1
Name: nijel-thepay
Version: 0.5
Summary: ThePay API library
Home-page: https://github.com/nijel/thepay
Author: Michal Čihař
Author-email: michal@cihar.com
License: LGPL
Keywords: payment,thepay
Platform: UNKNOWN
Requires-Python: >=3.5
Requires-Dist: suds-community
Requires-Dist: requests
Requires-Dist: six
